src/__init__.py
src/main.py
src/cli/__init__.py
src/cli/async_helper.py
src/cli/parsers.py
src/cli/command/__init__.py
src/cli/command/check.py
src/cli/command/schedule.py
src/repos/__init__.py
src/repos/carbon_intensity/__init__.py
src/repos/carbon_intensity/co2_signal.py
src/repos/carbon_intensity/file.py
src/repos/carbon_intensity/in_memory.py
src/repos/carbon_intensity/national_grid_eso.py
src/repos/carbon_intensity/protocol.py
carbon_guard-0.7.4.dist-info/METADATA
carbon_guard-0.7.4.dist-info/WHEEL
carbon_guard-0.7.4.dist-info/entry_points.txt
carbon_guard-0.7.4.dist-info/licenses/LICENSE.md
carbon_guard-0.7.4.dist-info/RECORD
