Metadata-Version: 2.3
Name: carbon_guard
Version: 0.7.4
Author-email: Adam Gardner <adam.gardner@armakuni.com>, Billie Thompson <billie.thompson@armakuni.com>
License-File: LICENSE.md
Requires-Python: >=3.11
Requires-Dist: dateparser>=1.2.0
Requires-Dist: httpx[brotli,http2]>=0.27.2
Requires-Dist: pydantic>=2.9.2
Requires-Dist: typer>=0.12.5
